{
  "collectionName": "components_section_main_sections",
  "info": {
    "displayName": "Section_main",
    "description": ""
  },
  "options": {},
  "attributes": {
    "effect_text": {
      "type": "text"
    },
    "title": {
      "type": "string",
      "required": true
    },
    "text": {
      "type": "text",
      "required": true
    },
    "button": {
      "type": "string",
      "required": true,
      "maxLength": 255,
      "minLength": 3
    },
    "slogan": {
      "type": "component",
      "repeatable": true,
      "component": "section.icon-grid"
    },
    "metadata": {
      "type": "component",
      "repeatable": false,
      "component": "section.section-metadata"
    },
    "image": {
      "type": "component",
      "repeatable": false,
      "component": "section.image-grid"
    }
  }
}
